gnsstime.py
gnsstime-0.0.9.dist-info/METADATA
gnsstime-0.0.9.dist-info/WHEEL
gnsstime-0.0.9.dist-info/top_level.txt
gnsstime-0.0.9.dist-info/RECORD
