Metadata-Version: 2.1
Name: gnsstime
Version: 0.0.9
Summary: Extended datetime for the gnss analysis.
Home-page: https://github.com/satoshi-pes/gnsstime.py
Author: Satoshi Kawamoto
Author-email: satoshi.pes@gmail.com
License: PSL
Keywords: gps,gnss,datetime
Platform: UNKNOWN
Classifier: Development Status :: 3 - Alpha
Classifier: License :: OSI Approved :: Python Software Foundation License
Classifier: Programming Language :: Python
Classifier: Topic :: Scientific/Engineering
